tupack/__init__.py
tupack/dates.py
tupack-0.0.1.dist-info/LICENSE
tupack-0.0.1.dist-info/METADATA
tupack-0.0.1.dist-info/WHEEL
tupack-0.0.1.dist-info/top_level.txt
tupack-0.0.1.dist-info/RECORD
