Metadata-Version: 2.1
Name: tupack
Version: 0.0.1
Summary: Tucar package
Home-page: https://github.com/TucarApp/tupack
Author: Admin
Author-email: admin@tucar.app
Project-URL: Bug Tracker, https://github.com/TucarApp/tupack/issues
Classifier: Programming Language :: Python :: 3
Classifier: License :: OSI Approved :: MIT License
Classifier: Operating System :: OS Independent
Requires-Python: >=3.10
License-File: LICENSE
